button_handler.py
circuitpython_button_handler-3.0.2.dist-info/licenses/LICENSE
circuitpython_button_handler-3.0.2.dist-info/METADATA
circuitpython_button_handler-3.0.2.dist-info/WHEEL
circuitpython_button_handler-3.0.2.dist-info/top_level.txt
circuitpython_button_handler-3.0.2.dist-info/RECORD
