Metadata-Version: 2.4
Name: circuitpython-button-handler
Version: 3.0.2
Summary: This helper library simplifies the usage of buttons with CircuitPython, by detecting and differentiating button inputs, returning a set of the inputs and calling their corresponding functions.
Author: EGJ Moorington
License: MIT
Project-URL: Homepage, https://github.com/EGJ-Moorington/CircuitPython_Button_Handler
Keywords: adafruit,blinka,circuitpython,micropython,button_handler,button,short,long,double,triple,multi,keypad,key,press,helper
Classifier: Intended Audience :: Developers
Classifier: Topic :: Software Development :: Libraries
Classifier: Topic :: Software Development :: Embedded Systems
Classifier: Topic :: System :: Hardware
Classifier: License :: OSI Approved :: MIT License
Classifier: Programming Language :: Python :: 3
License-File: LICENSE
Requires-Dist: Adafruit-Blinka
Provides-Extra: optional
Dynamic: license-file
